main.py
setup.py
Larger_Batch_CTR.egg-info/PKG-INFO
Larger_Batch_CTR.egg-info/SOURCES.txt
Larger_Batch_CTR.egg-info/dependency_links.txt
Larger_Batch_CTR.egg-info/requires.txt
Larger_Batch_CTR.egg-info/top_level.txt